bsv/__init__.py
bsv/aes_cbc.py
bsv/base58.py
bsv/broadcaster.py
bsv/chaintracker.py
bsv/constants.py
bsv/curve.py
bsv/encrypted_message.py
bsv/fee_model.py
bsv/hash.py
bsv/http_client.py
bsv/keys.py
bsv/merkle_path.py
bsv/polynomial.py
bsv/signed_message.py
bsv/transaction.py
bsv/transaction_input.py
bsv/transaction_output.py
bsv/transaction_preimage.py
bsv/utils.py
bsv/broadcasters/__init__.py
bsv/broadcasters/arc.py
bsv/broadcasters/default.py
bsv/broadcasters/whatsonchain.py
bsv/chaintrackers/__init__.py
bsv/chaintrackers/default.py
bsv/chaintrackers/whatsonchain.py
bsv/fee_models/__init__.py
bsv/fee_models/live_policy.py
bsv/fee_models/satoshis_per_kilobyte.py
bsv/hd/__init__.py
bsv/hd/bip32.py
bsv/hd/bip39.py
bsv/hd/bip44.py
bsv/hd/wordlist/chinese_simplified.txt
bsv/hd/wordlist/english.txt
bsv/script/__init__.py
bsv/script/script.py
bsv/script/spend.py
bsv/script/type.py
bsv/script/unlocking_template.py
bsv_sdk-1.0.10.dist-info/licenses/LICENSE.txt
bsv_sdk-1.0.10.dist-info/METADATA
bsv_sdk-1.0.10.dist-info/WHEEL
bsv_sdk-1.0.10.dist-info/top_level.txt
bsv_sdk-1.0.10.dist-info/RECORD
