Metadata-Version: 2.4
Name: bsv-sdk
Version: 1.0.10
Summary: BSV BLOCKCHAIN | Software Development Kit for Python
Home-page: https://github.com/bitcoin-sv/py-sdk
Author: Aaron
Author-email: aaron@scrypt.io
Project-URL: Bug Tracker, https://github.com/bitcoin-sv/py-sdk/issues
Keywords: bsv
Classifier: Intended Audience :: Developers
Classifier: Programming Language :: Python :: 3.9
Classifier: Programming Language :: Python :: 3.10
Classifier: Programming Language :: Python :: 3.11
Classifier: Programming Language :: Python :: 3.12
Classifier: Operating System :: OS Independent
Requires-Python: >=3.9
License-File: LICENSE.txt
Requires-Dist: pycryptodomex>=3.20.0
Requires-Dist: coincurve>=20.0.0
Requires-Dist: requests>=2.32.3
Requires-Dist: aiohttp>=3.10.5
Provides-Extra: test
Requires-Dist: pytest>=8.3.3; extra == "test"
Requires-Dist: pytest-asyncio>=0.24.0; extra == "test"
Requires-Dist: ecdsa>=0.19.0; extra == "test"
Dynamic: license-file
